django_cloudflare_restrictor/__init__.py
django_cloudflare_restrictor/cloudflare_ips.py
django_cloudflare_restrictor/middleware.py
django_cloudflare_restrictor/management/__init__.py
django_cloudflare_restrictor/management/commands/__init__.py
django_cloudflare_restrictor/management/commands/check_cloudflare_ips.py
django_cloudflare_restrictor-1.0.2.dist-info/LICENSE.md
django_cloudflare_restrictor-1.0.2.dist-info/METADATA
django_cloudflare_restrictor-1.0.2.dist-info/WHEEL
django_cloudflare_restrictor-1.0.2.dist-info/top_level.txt
django_cloudflare_restrictor-1.0.2.dist-info/RECORD
