Metadata-Version: 2.1
Name: django-cloudflare-restrictor
Version: 1.0.2
Summary: Django package to restrict access just to cloudflare workers
Home-page: https://github.com/diffractive/django-cloudflare-restrictor
Author: Kevin Campbell
Author-email: kev@diffractive.io
Requires-Python: >=3.6
License-File: LICENSE.md
Requires-Dist: Django (>=2.0)
